CHANGELOG.rst
LICENSE
MANIFEST.in
README.rst
setup.cfg
setup.py
flask_apispec/__init__.py
flask_apispec/annotations.py
flask_apispec/apidoc.py
flask_apispec/extension.py
flask_apispec/paths.py
flask_apispec/utils.py
flask_apispec/views.py
flask_apispec/wrapper.py
flask_apispec/static/index.html
flask_apispec/static/o2c.html
flask_apispec/static/swagger-ui.js
flask_apispec/static/swagger-ui.min.js
flask_apispec/static/css/print.css
flask_apispec/static/css/reset.css
flask_apispec/static/css/screen.css
flask_apispec/static/css/style.css
flask_apispec/static/css/typography.css
flask_apispec/static/fonts/droid-sans-v6-latin-700.eot
flask_apispec/static/fonts/droid-sans-v6-latin-700.svg
flask_apispec/static/fonts/droid-sans-v6-latin-700.ttf
flask_apispec/static/fonts/droid-sans-v6-latin-700.woff
flask_apispec/static/fonts/droid-sans-v6-latin-700.woff2
flask_apispec/static/fonts/droid-sans-v6-latin-regular.eot
flask_apispec/static/fonts/droid-sans-v6-latin-regular.svg
flask_apispec/static/fonts/droid-sans-v6-latin-regular.ttf
flask_apispec/static/fonts/droid-sans-v6-latin-regular.woff
flask_apispec/static/fonts/droid-sans-v6-latin-regular.woff2
flask_apispec/static/images/explorer_icons.png
flask_apispec/static/images/favicon-16x16.png
flask_apispec/static/images/favicon-32x32.png
flask_apispec/static/images/favicon.ico
flask_apispec/static/images/logo_small.png
flask_apispec/static/images/pet_store_api.png
flask_apispec/static/images/throbber.gif
flask_apispec/static/images/wordnik_api.png
flask_apispec/static/lang/en.js
flask_apispec/static/lang/es.js
flask_apispec/static/lang/pt.js
flask_apispec/static/lang/ru.js
flask_apispec/static/lang/tr.js
flask_apispec/static/lang/translator.js
flask_apispec/static/lang/zh-cn.js
flask_apispec/static/lib/backbone-min.js
flask_apispec/static/lib/handlebars-2.0.0.js
flask_apispec/static/lib/highlight.7.3.pack.js
flask_apispec/static/lib/jquery-1.8.0.min.js
flask_apispec/static/lib/jquery.ba-bbq.min.js
flask_apispec_rovanion.egg-info/PKG-INFO
flask_apispec_rovanion.egg-info/SOURCES.txt
flask_apispec_rovanion.egg-info/dependency_links.txt
flask_apispec_rovanion.egg-info/not-zip-safe
flask_apispec_rovanion.egg-info/requires.txt
flask_apispec_rovanion.egg-info/top_level.txt