Metadata-Version: 1.1
Name: flask-apispec-rovanion
Version: 0.6.0.post0
Summary: Build and document REST APIs with Flask and apispec
Home-page: https://github.com/jmcarp/flask-apispec
Author: Joshua Carp
Author-email: jm.carp@gmail.com
License: MIT
Keywords: flask marshmallow webargs apispec
Platform: UNKNOWN
Classifier: Development Status :: 4 - Beta
Classifier: Intended Audience :: Developers
Classifier: License :: OSI Approved :: MIT License
Classifier: Natural Language :: English
Classifier: Programming Language :: Python :: 2
Classifier: Programming Language :: Python :: 2.7
Classifier: Programming Language :: Python :: 3
Classifier: Programming Language :: Python :: 3.4
Classifier: Programming Language :: Python :: 3.5
Classifier: Programming Language :: Python :: 3.6
